{
  "id": "0ceef96a-d5d6-4910-8c00-95b453ce33b1",
  "type": "insight",
  "timestamp": "2025-11-20T00:27:19.000Z",
  "title": "<div><tt>- Full model checkpoint (quarterly)</tt></div>",
  "content": "<div><tt>- Full model checkpoint (quarterly)</tt></div>\n<div><tt><br></tt></div>\n<div><tt>### **24. Evaluation Benchmarks**</tt></div>\n<div><tt><br></tt></div>\n<div><tt>**Linguistic Tasks:**</tt></div>\n<div><tt><br></tt></div>\n<div><tt>- POS Tagging: &gt97% accuracy (UD English)</tt></div>\n<div><tt>- Dependency Parsing: &gt92% UAS, &gt90% LAS</tt></div>\n<div><tt>- NER: &gt90% F1 (CoNLL-2003)</tt></div>\n<div><tt>- SRL: &gt87% F1 (CoNLL-2012)</tt></div>\n<div><tt>- AMR Parsing: &gt85% Smatch</tt></div>\n<div><tt><br></tt></div>\n<div><tt>**Rhetorical Tasks:**</tt></div>\n<div><tt><br></tt></div>\n<div><tt>- Ethos Detection: &gt75% F1</tt></div>\n<div><tt>- Pathos Detection: &gt80% F1</tt></div>\n<div><tt>- Fallacy Detection: &gt75% F1</tt></div>\n<div><tt>- Propaganda Detection: &gt75% F1</tt></div>\n<div><tt><br></tt></div>\n<div><tt>**Multimodal:**</tt></div>\n<div><tt><br></tt></div>\n<div><tt>- Image-Text Retrieval: &gt85% R@1</tt></div>\n<div><tt>- VQA: &gt75% accuracy</tt></div>\n<div><tt>- Multimodal Sentiment: &gt80% F1</tt></div>\n<div><tt><br></tt></div>\n<div><tt>**Meta-Learning:**</tt></div>\n<div><tt><br></tt></div>\n<div><tt>- 1-shot Classification: &gt50% accuracy</tt></div>\n<div><tt>- 5-shot Classification: &gt65% accuracy</tt></div>",
  "context": "From document: # **Theoria Linguae Machina: Comprehensive Design Document for the… — chunk 47 (chunk 47/57)",
  "tags": [
    "paragraph",
    "html",
    "chunked",
    "chunk-strategy-markdown-semantic"
  ],
  "category": "general",
  "documentId": "657aecac6f7fd18489e5adc55f9e6f82",
  "relatedUnits": [],
  "keywords": [
    "accuracy",
    "detection",
    "gt75",
    "tasks",
    "parsing"
  ],
  "sectionType": "paragraph",
  "hierarchyLevel": 0
}