{
  "id": "154d7fa5-8e19-42dc-9257-8af6e8bb79bb",
  "type": "insight",
  "timestamp": "2025-11-05T21:42:26.000Z",
  "title": "<li><b>Docs:</b><br><u>https://dashboard.clearbit.com/docs</u><br></li>",
  "content": "<li><b>Docs:</b><br><u>https://dashboard.clearbit.com/docs</u><br></li>\n</ul>\n<div><br></div>\n<div><b>4. Apollo API</b></div>\n<div><b><h2>Purpose: Business contacts, verified emails, company data</h2></b></div>\n<ul>\n<li><b>API Key:</b>YOUR_APOLLO_API_KEY_HERE</li>\n<li><b>Docs:</b><br><u>https://apolloio.github.io/apollo-api-docs/</u><br></li>\n</ul>\n<div><br></div>\n<div><b>5. Hunter.io API</b></div>\n<div><b><h2>Purpose: Email lookup + verification</h2></b></div>\n<ul>\n<li><b>API Key:</b>YOUR_HUNTER_API_KEY_HERE</li>\n<li><b>Docs:</b><br><u>https://hunter.io/api-documentation</u><br></li>\n</ul>\n<div><br></div>\n<div><b>6. People Data Labs (PDL)</b></div>\n<div><b><h2>Purpose: Company + people enrichment</h2></b></div>\n<ul>\n<li><b>API Key:</b>YOUR_PDL_API_KEY_HERE</li>\n<li><b>Docs:</b>https://docs.peopledatalabs.com/docs</li>\n</ul>\n<div><br></div>\n<div><b>7. FullContact API</b></div>\n<div><b><h2>Purpose: Contact enrichment &amp business profiles</h2></b></div>\n<ul>\n<li><b>API Key:</b>YOUR_FULLCONTACT_API_KEY_HERE</li>\n<li><b>Docs:</b>https://www.fullcontact.com/developer/docs/</li>\n</ul>\n<div><br></div>\n<div><b>8. Crunchbase API</b></div>\n<div><b><h2>Purpose: Company funding, financials, employees</h2></b></div>",
  "context": "From document: data enrichment strategy for ucc-mca intelligence platform — chunk 20 (chunk 20/32)",
  "tags": [
    "paragraph",
    "html",
    "chunked",
    "chunk-strategy-markdown-semantic"
  ],
  "category": "programming",
  "documentId": "42efb0f415b2f324521d2959a50f91bf",
  "relatedUnits": [],
  "keywords": [
    "docs",
    "https",
    "purpose",
    "company",
    "apollo"
  ],
  "sectionType": "paragraph",
  "hierarchyLevel": 0
}