{
  "id": "1cf851c4-12d5-47d7-8945-18bc0ec4b179",
  "type": "insight",
  "timestamp": "2025-02-12T16:21:40.000Z",
  "title": "<div>Write a substantive draft with a minimum of 350 - 650 words, each paragraph",
  "content": "<div>Write a substantive draft with a minimum of 350 - 650 words, each paragraph being approximately 4 - 6 sentences or more.</div>\n<div>Include descriptive devices such as metaphor, similes, and/or personification.</div>\n<div>Demonstrate that all aspects of your topic have been considered.</div>\n<div>Use the plagiarism tool to check your summary against unintended plagiarism.</div>\n<div>Refer to the guidelines below to complete each phase of your essay following the required APA format:</div>\n<div>APA (7th Edition) Student Sample Paper</div>\n<div>APA Formatting and Style Guide (7th Edition)</div>\n<div>Spell-check your essay.</div>\n<div>Save your work using the proper naming convention and attach your file to submit.</div>\n<div>Estimated Time for Completion</div>\n<div>The estimated time to complete this activity is 3 - 4 hours.</div>\n<div><br></div>\n<div>rubric for rough draft narrative essay:</div>\n<div><br></div>\n<div>Week 2 Assignment</div>\n<div>Week 2 Assignment</div>\n<div>Criteria  Ratings  Pts</div>\n<div>This criterion is linked to a Learning OutcomeRough Draft : Introduction</div>\n<div>5 pts</div>\n<div>Full Credit</div>\n<div>Successfully adhered to the instructions and guidelines provided in the prewriting exercise.</div>",
  "context": "From document: Week 2 Canvas Data Dump:  Week 2 | Overview: — chunk 17 (chunk 17/24)",
  "tags": [
    "paragraph",
    "html",
    "chunked",
    "chunk-strategy-markdown-semantic"
  ],
  "category": "research",
  "documentId": "0d4efdf09cb66aedfded39b9a4c3edf4",
  "relatedUnits": [],
  "keywords": [
    "your",
    "draft",
    "essay",
    "each",
    "plagiarism"
  ],
  "sectionType": "paragraph",
  "hierarchyLevel": 0
}