{
  "id": "1d46f845-1225-4301-96b5-348c9d3b6590",
  "type": "insight",
  "timestamp": "2020-09-30T18:08:27.000Z",
  "title": "<div><br></div>",
  "content": "<div><br></div>\n<div>There is a much bigger past happening that we should never forget and it is already slipping out of the social conscious: &quot[The Holocaust] was the greatest crime of the 20th century, but Gen Z and millennial Americans remain hugely ignorant about [it]. One in 10 young Americans believes that the Holocaust never happened, while almost a quarter — 23% — believe it is a myth or that the number of Jews who were killed has been exaggerated&quot (vice.com). When a society forgets about its past transgressions that society is doomed to repeat the same mistakes.</div>\n<div><br></div>\n<div>In the early 20th century, Germany, Italy, and Japan caught a severe case of Nationalism and Fascism and then went on to set the entire world on fire. </div>\n<div><br></div>\n<div>In the early 21st Century (AKA Today), Nationalism and Fascism (disguised in a different set of stage clothes) is spreading once again...not only over seas, but on our own soil as well.</div>\n<div><br></div>\n<div>As George Carlin foretold, &quotWhen fascism comes to America, it will not be in brown and black shirts. It will not be with jack-boots. It will be Nike sneakers and Smiley shirts.&quot And we are not doing a single thing about it. We are fat and comfortable Americans who never had to fight for anything other than a place in a decent college or for a coveted job at Google. In other countries the people riot when their rights are taken from them or when democracy fails them. Most of us do not. We do not go to bed at night worried about being collateral dead by a drone strike that was meant for someone else who may have been involved in something that might've happened.</div>",
  "context": "From document: On the yearly anniversary of 9/11 Americans all over the country share… — chunk 2 (chunk 2/4)",
  "tags": [
    "paragraph",
    "html",
    "chunked",
    "chunk-strategy-markdown-semantic"
  ],
  "category": "general",
  "documentId": "39262d360887bd3797e2011ff70b41fe",
  "relatedUnits": [],
  "keywords": [
    "that",
    "about",
    "never",
    "quot",
    "century"
  ],
  "sectionType": "paragraph",
  "hierarchyLevel": 0
}