{
  "id": "1d8fd2da-18c7-4438-bb6c-4797d1d9e1b9",
  "type": "insight",
  "timestamp": "2025-04-12T21:23:06.000Z",
  "title": "<div><tt><br></tt></div>",
  "content": "<div><tt><br></tt></div>\n<div><tt>---</tt></div>\n<div><tt><br></tt></div>\n<div><tt>### IV. | NEXT STEPS (PHASE 3 INITIATION OPTIONS)</tt></div>\n<div><tt><br></tt></div>\n<div><tt>1. **Start Phase 3.0 Fusion:**  </tt></div>\n<div><tt>   Launch `::MAP_OS_4BLOOM` master architecture thread — system-wide nesting begins.</tt></div>\n<div><tt><br></tt></div>\n<div><tt>2. **Spawn Focus Threads:**  </tt></div>\n<div><tt>   Open deep dives into submodules (`::GR1ND3R_LOGIK`, `::MET4_CORE`, etc.).</tt></div>\n<div><tt><br></tt></div>\n<div><tt>3. **Deploy EDU Builders:**  </tt></div>\n<div><tt>   Generate pedagogy toolkits, cross-field syllabi, and curriculum seeds.</tt></div>\n<div><tt><br></tt></div>\n<div><tt>4. **Render Consumer Formats:**  </tt></div>\n<div><tt>   Begin PDF, GitHub, Zine, and App interfaces from modular exports.</tt></div>\n<div><tt><br></tt></div>\n<div><tt>5. **Symbol System Assignment:**  </tt></div>\n<div><tt>   Assign glyphs to each entity, logic layer, and medium.</tt></div>\n<div><tt><br></tt></div>\n<div><tt>---</tt></div>\n<div><tt><br></tt></div>\n<div><tt>::REF_ID = SYS_PHASE_2.5_COMPLETE  </tt></div>\n<div><tt>::STATUS = LOCKED  </tt></div>\n<div><tt>::NEXT = [PHASE_3.0_READY]  </tt></div>",
  "context": "From document: ::ARCHIVE_ENTRY_001 — chunk 168 (chunk 168/171)",
  "tags": [
    "paragraph",
    "html",
    "chunked",
    "chunk-strategy-markdown-semantic"
  ],
  "category": "general",
  "documentId": "a7b09d3ba5b3b15755de78dc66d7da4b",
  "relatedUnits": [],
  "keywords": [
    "next",
    "phase",
    "system",
    "steps",
    "initiation"
  ],
  "sectionType": "paragraph",
  "hierarchyLevel": 0
}