{
  "id": "2273a2c9-d111-4766-9dcd-21a8f601dd69",
  "type": "insight",
  "timestamp": "2025-02-04T20:15:04.000Z",
  "title": "<div>A:</div>",
  "content": "<div>A:</div>\n<div>https://youtu.be/czw2e6Za5EA</div>\n<div>Check this out</div>\n<div><br></div>\n<div>R:</div>\n<div>Thats what I was talking about</div>\n<div>Thats craaaaaaazyyy</div>\n<div><br></div>\n<div>A:</div>\n<div>Yes you can play instruments with more expression now and control multiple parameters with your finger. It looks so cool</div>\n<div><br></div>\n<div>R:</div>\n<div>So cooolll!!!!!!</div>\n<div><br></div>\n<div><br></div>\n<div>____________________________________________________________</div>\n<div><br></div>\n<div><br></div>\n<div><h2>Dustin and Anthony - June, 2nd 2024</h2></div>\n<div><br></div>\n<div>Dustin's first set of messages:</div>\n<div>https://drive.google.com/file/d/18lQoGtl6GNZZUEHtUDQCuwXhgpxNZOy9/view?usp=drivesdk</div>\n<div>https://drive.google.com/file/d/1CgaHHqz4-zBd9wDRLkzAh5sID82smErp/view?usp=drivesdk</div>\n<div>https://drive.google.com/file/d/1Nb4Dhfd2M8oE3SyBsygHkDDHXBQj38Jg/view?usp=drivesdk</div>\n<div>https://drive.google.com/file/d/1ct5kxsLDSI6bKq1nhkHfyAaR-FlI-u94/view?usp=drivesdk</div>\n<div><br></div>\n<div>Anthony's first message:</div>\n<div>Toby is so fucking sick</div>\n<div>https://music.apple.com/us/album/tobey/[REDACTED:PHONE NUMBER]?i=[REDACTED:PHONE NUMBER]</div>\n<div>Wow. Beautiful </div>",
  "context": "From document: Conversations on Music and Art and Life — chunk 4 (chunk 4/10)",
  "tags": [
    "paragraph",
    "html",
    "chunked",
    "chunk-strategy-markdown-semantic"
  ],
  "category": "general",
  "documentId": "1866b79d0ff31ac7637a06bb29bd0781",
  "relatedUnits": [],
  "keywords": [
    "https",
    "drive",
    "google",
    "file",
    "view"
  ],
  "sectionType": "paragraph",
  "hierarchyLevel": 0
}