{
  "id": "4f719a84-c7e2-45c5-9e64-60dd726aae14",
  "type": "insight",
  "timestamp": "2025-04-12T21:23:06.000Z",
  "title": "<div><tt>&gt Project = vessel / output / expression  </tt></div>",
  "content": "<div><tt>&gt Project = vessel / output / expression  </tt></div>\n<div><tt><br></tt></div>\n<div><tt>---</tt></div>\n<div><tt><br></tt></div>\n<div><tt>### II. LOGIC CLASSIFICATION SYSTEM: REALITY vs DREAM</tt></div>\n<div><tt><br></tt></div>\n<div><tt>Each project or tool will be tagged with a *dominant logic mode*, which informs tone, structure, and method:</tt></div>\n<div><tt><br></tt></div>\n<div><tt>| Project | Mode | Notes |</tt></div>\n<div><tt>|---------|------|-------|</tt></div>\n<div><tt>| `::Q_v33R` | **Reality Logic** | Memoir, interviews, identity &amp community |</tt></div>\n<div><tt>| `::GR1ND3R` | **Dream Logic** | Dread, unreliable memory, narrative collapse |</tt></div>\n<div><tt>| `::MET4` | **Hybrid** | Structured myth, speculative theology |</tt></div>\n<div><tt>| `::FLOAT1NG.P01NTS` | **Surreal** | Visual grammar, fragmented poetics |</tt></div>\n<div><tt>| `::ETCETER4` | **Reality-inflected, dream-bent** | Lyric truth, audio collage |</tt></div>\n<div><tt>| `::DR34M.L0G1K` | **Dream** | Symbolic AI, subconscious system UI |</tt></div>\n<div><tt>| `::KONS0L` | **Reality** | Citation, analysis, archival order |</tt></div>\n<div><tt><br></tt></div>\n<div><tt>Tagging projects this way allows:</tt></div>",
  "context": "From document: ::ARCHIVE_ENTRY_001 — chunk 65 (chunk 65/171)",
  "tags": [
    "paragraph",
    "html",
    "chunked",
    "chunk-strategy-markdown-semantic"
  ],
  "category": "research",
  "documentId": "a7b09d3ba5b3b15755de78dc66d7da4b",
  "relatedUnits": [],
  "keywords": [
    "logic",
    "reality",
    "dream",
    "project",
    "system"
  ],
  "sectionType": "paragraph",
  "hierarchyLevel": 0
}