{
  "id": "5e4d3086-05f3-408e-b9f4-a777dc9926ff",
  "type": "insight",
  "timestamp": "2025-02-12T16:21:40.000Z",
  "title": "<div><br></div>",
  "content": "<div><br></div>\n<div>Dialogue</div>\n<div><br></div>\n<div><br></div>\n<div>Finally, dialogue can effectively bring characters and scenes to life within a narrative essay. It allows readers to hear directly from the characters themselves or may show what a character is thinking, and it adds depth and personality to their actions and emotions. Make sure dialogue feels natural and not forced; otherwise, it can pull readers out of the story.</div>\n<div><br></div>\n<div>Good narration should be clear and concise yet evocative enough to capture readers' attention immediately. Some things to consider when using dialogue are:</div>\n<div><br></div>\n<div>Place quotation marks around words</div>\n<div>Start a new paragraph when a different character speaks</div>\n<div>Make it realistic by using slang or colloquialisms</div>\n<div>Make it clear to your reader who is speaking</div>\n<div>Be sure to use commas with your dialogue tags</div>\n<div>Overall, the elements of audience, purpose, and dialogue form the foundation of any good narrative essay: knowing your audience, having a clear purpose in mind, and utilizing effective dialogue when appropriate.</div>\n<div><br></div>\n<div>Week 2 | Sentence Structure and Varied Sentence Structure:</div>",
  "context": "From document: Week 2 Canvas Data Dump:  Week 2 | Overview: — chunk 9 (chunk 9/24)",
  "tags": [
    "paragraph",
    "html",
    "chunked",
    "chunk-strategy-markdown-semantic"
  ],
  "category": "writing",
  "documentId": "0d4efdf09cb66aedfded39b9a4c3edf4",
  "relatedUnits": [],
  "keywords": [
    "dialogue",
    "readers",
    "make",
    "clear",
    "when"
  ],
  "sectionType": "paragraph",
  "hierarchyLevel": 0
}