{
  "id": "5f2252c4-3ea4-44b5-92d4-71a2ab7cfbcf",
  "type": "insight",
  "timestamp": "2025-04-12T21:23:06.000Z",
  "title": "<div><tt><br></tt></div>",
  "content": "<div><tt><br></tt></div>\n<div><tt>**Response:**  </tt></div>\n<div><tt><br></tt></div>\n<div><tt>---</tt></div>\n<div><tt><br></tt></div>\n<div><tt>### |[PHASE 2.5: EXPANSION + CLASSIFICATION + SYSTEM MAPPING]|</tt></div>\n<div><tt><br></tt></div>\n<div><tt>**Goal:** Cascade ecosystem into classifiable, modular, recursive nodes  </tt></div>\n<div><tt>**Scope:** Creative Identity → Project Logic → Educational Field → Business Form</tt></div>\n<div><tt><br></tt></div>\n<div><tt>---</tt></div>\n<div><tt><br></tt></div>\n<div><tt>### I. ARTIST ID vs PROJECT: CORE DISTINCTION</tt></div>\n<div><tt><br></tt></div>\n<div><tt>| Category | Definition | Examples |</tt></div>\n<div><tt>|----------|------------|----------|</tt></div>\n<div><tt>| **ARTIST ID** | A role, lens, or voice used to *generate* work. May span formats or mediums. | `::4_bl00m`, `::ETCETER4`, `::Q_v33R` |</tt></div>\n<div><tt>| **PROJECT** | A distinct system or output built *by or through* one or more artist IDs. Often has timeline, audience, and internal rules. | `::GR1ND3R`, `::MET4morfoses`, `::FLOAT1NG.P01NTS` |</tt></div>\n<div><tt><br></tt></div>\n<div><tt>&gt Think:  </tt></div>\n<div><tt>&gt Artist ID = engine / operator / persona  </tt></div>",
  "context": "From document: ::ARCHIVE_ENTRY_001 — chunk 64 (chunk 64/171)",
  "tags": [
    "paragraph",
    "html",
    "chunked",
    "chunk-strategy-markdown-semantic"
  ],
  "category": "general",
  "documentId": "a7b09d3ba5b3b15755de78dc66d7da4b",
  "relatedUnits": [],
  "keywords": [
    "artist",
    "project",
    "system",
    "response",
    "phase"
  ],
  "sectionType": "paragraph",
  "hierarchyLevel": 0
}