{
  "id": "6a8d6982-2cc7-45b7-90a6-38258c110d70",
  "type": "insight",
  "timestamp": "2025-02-06T01:47:14.000Z",
  "title": "</td><td valign=\"top\" style=\"border-style: solid; border-width: 1.0px 1.0px 1.0p",
  "content": "</td><td valign=\"top\" style=\"border-style: solid; border-width: 1.0px 1.0px 1.0px 1.0px; border-color: #ccc; padding: 3.0px 5.0px 3.0px 5.0px; min-width: 70px\"><div>The Trickster Mentor</div>\n</td><td valign=\"top\" style=\"border-style: solid; border-width: 1.0px 1.0px 1.0px 1.0px; border-color: #ccc; padding: 3.0px 5.0px 3.0px 5.0px; min-width: 70px\"><div>The Silent Observer</div>\n</td></tr>\n<tr><td valign=\"top\" style=\"border-style: solid; border-width: 1.0px 1.0px 1.0px 1.0px; border-color: #ccc; padding: 3.0px 5.0px 3.0px 5.0px; min-width: 70px\"><div>“Which force dictates fate: logic, chaos, or prophecy?”</div>\n</td><td valign=\"top\" style=\"border-style: solid; border-width: 1.0px 1.0px 1.0px 1.0px; border-color: #ccc; padding: 3.0px 5.0px 3.0px 5.0px; min-width: 70px\"><div>The Divine Judge</div>\n</td><td valign=\"top\" style=\"border-style: solid; border-width: 1.0px 1.0px 1.0px 1.0px; border-color: #ccc; padding: 3.0px 5.0px 3.0px 5.0px; min-width: 70px\"><div>The Trickster God</div>\n</td><td valign=\"top\" style=\"border-style: solid; border-width: 1.0px 1.0px 1.0px 1.0px; border-color: #ccc; padding: 3.0px 5.0px 3.0px 5.0px; min-width: 70px\"><div>The Oracle</div>\n</td></tr>\n<tr><td valign=\"top\" style=\"border-style: solid; border-width: 1.0px 1.0px 1.0px 1.0px; border-color: #ccc; padding: 3.0px 5.0px 3.0px 5.0px; min-width: 70px\"><div>“What should be feared most: loss, change, or the unknown?”</div>",
  "context": "From document: RPG Character System (Fully Integrated into Weekly Modules) — chunk 406 (chunk 406/555)",
  "tags": [
    "paragraph",
    "html",
    "chunked",
    "chunk-strategy-markdown-semantic"
  ],
  "category": "general",
  "documentId": "1536a93a8157b0425ef5d110f12dc007",
  "relatedUnits": [],
  "keywords": [
    "border",
    "style",
    "width",
    "valign",
    "solid"
  ],
  "sectionType": "paragraph",
  "hierarchyLevel": 0
}