{
  "id": "762e9a0a-2342-4ca1-b692-d1dddd3d9d1f",
  "type": "insight",
  "timestamp": "2025-12-04T16:48:25.000Z",
  "title": "<div><tt>| UI Blur/Clarity | Visual | Anxiety, Reverb, Lightness |</tt></div>",
  "content": "<div><tt>| UI Blur/Clarity | Visual | Anxiety, Reverb, Lightness |</tt></div>\n<div><tt>----</tt></div>\n<div><tt>____</tt></div>\n<div><tt>____</tt></div>\n<div><tt>____</tt></div>",
  "context": "From document: # synth-wave-modules — chunk 51 (chunk 51/51)",
  "tags": [
    "paragraph",
    "html",
    "chunked",
    "chunk-strategy-markdown-semantic"
  ],
  "category": "general",
  "documentId": "1f0200e52addd3bec3d0beb78cca4a02",
  "relatedUnits": [],
  "keywords": [
    "____",
    "blur",
    "clarity",
    "visual",
    "anxiety"
  ],
  "sectionType": "paragraph",
  "hierarchyLevel": 0
}