{
  "id": "788a84b6-6947-4b3d-a07f-383c013ec808",
  "type": "insight",
  "timestamp": "2025-10-07T15:19:53.000Z",
  "title": "<div><br></div>",
  "content": "<div><br></div>\n<div>You</div>\n<div>Now, </div>\n<div><br></div>\n<div>John Monforte</div>\n<div>You know what I </div>\n<div><br></div>\n<div>You</div>\n<div>yes, </div>\n<div><br></div>\n<div>John Monforte</div>\n<div>mean? That what I'm </div>\n<div><br></div>\n<div>You</div>\n<div>I </div>\n<div><br></div>\n<div>John Monforte</div>\n<div>saying, </div>\n<div><br></div>\n<div>You</div>\n<div>totally </div>\n<div><br></div>\n<div>John Monforte</div>\n<div>like </div>\n<div><br></div>\n<div>You</div>\n<div>get, </div>\n<div><br></div>\n<div>John Monforte</div>\n<div>simplified. </div>\n<div><br></div>\n<div>You</div>\n<div>I totally get it. I want to I like your idea. What I'm trying to say to you, which would be cool, right? Other than just watching it, what if it had things that were always changing and each time it happened, right? They could have prop bets. Like, oh, Croc is going to say, uh, uh, he's going to side with whoever on the argument or he's going to do that. We can have ways to have a betting. </div>\n<div><br></div>\n<div>John Monforte</div>\n<div>It's, it's going to be, it's going to be hard to make uh, things wager on on the site. That's, you know what I'm saying? But what you could do is make it where you can make it like press one to influence rock. </div>",
  "context": "From document: Call with John Monforte — chunk 9 (chunk 9/13)",
  "tags": [
    "paragraph",
    "html",
    "chunked",
    "chunk-strategy-markdown-semantic"
  ],
  "category": "general",
  "documentId": "575c44b5a3667dd014278be4c7bc060e",
  "relatedUnits": [],
  "keywords": [
    "john",
    "monforte",
    "what",
    "going",
    "that"
  ],
  "sectionType": "paragraph",
  "hierarchyLevel": 0
}