{
  "id": "7d40e5d4-396e-4eda-8c55-4c1df0dc58ab",
  "type": "insight",
  "timestamp": "2025-07-05T16:03:17.000Z",
  "title": "<div><br></div>",
  "content": "<div><br></div>\n<div>---</div>\n<div><br></div>\n<div>### 🔗 Channel 42–53</div>\n<div><br></div>\n<div>- **Gate 42.3** – Completion / Growth (Design)</div>\n<div>  - **Line 3** = *Learning Through Error*</div>\n<div>  - You mature by testing ideas and allowing full cycles.</div>\n<div>- **Gate 53.5** – Beginning / Initiative (Personality)</div>\n<div>  - **Line 5** = *Visionary Starter*</div>\n<div>  - You initiate not just for self, but for systems. Your beginnings ripple outward.</div>\n<div><br></div>\n<div>**Narrative**: You begin visionary arcs and carry them through the mess until they complete. You're not just an idea-starter—you're an arc-weaver.</div>\n<div><br></div>\n<div>---</div>\n<div><br></div>\n<div>### 🔗 Channel 59–6</div>\n<div><br></div>\n<div>- **Gate 59.6** – Sexuality / Dispersion (Design)</div>\n<div>  - **Line 6** = *Role Model of Intimacy*</div>\n<div>  - Your lessons in connection come later in life. You’re meant to *demonstrate evolved intimacy*.</div>\n<div>- **Gate 6.5** – Friction / Universalization (Personality)</div>\n<div>  - **Line 5** = *Diplomatic Bridge-Builder*</div>\n<div>  - You're here to resolve tension between people/groups. You bring intimacy to public systems.</div>",
  "context": "From document: --- — chunk 26 (chunk 26/73)",
  "tags": [
    "paragraph",
    "html",
    "chunked",
    "chunk-strategy-markdown-semantic"
  ],
  "category": "writing",
  "documentId": "ca52aa9034f8326c145c920d4b105117",
  "relatedUnits": [],
  "keywords": [
    "gate",
    "line",
    "intimacy",
    "channel",
    "design"
  ],
  "sectionType": "paragraph",
  "hierarchyLevel": 0
}