{
  "id": "89b2f6e9-fb51-412c-9d6c-ede9e5d49375",
  "type": "insight",
  "timestamp": "2025-02-12T16:23:09.000Z",
  "title": "<div><br></div>",
  "content": "<div><br></div>\n<div>Now, go back and read all of your Weekly Writing Warm-up entries from the past six weeks. What do you notice about your entries? Do you see improvements? What are they? What benefit has this ongoing assignment given you during this class?</div>\n<div><br></div>\n<div>Save your completed Week 6 Weekly Writing Warm-Up using the proper naming convention.</div>\n<div>Estimated Time for Completion</div>\n<div>The estimated time to complete this activity is 5 minutes.</div>\n<div><br></div>\n<div>Completion</div>\n<div>The naming convention is ENG101_wk#_warm_up_firstintiallastname_date—for example, ENG101_wk6_warm_up_jsmith_mmddyyyy.</div>\n<div>Submit the Week 6 Weekly Writing Warm-Up by the end of the week. See the video below to review the process.</div>\n<div><br></div>\n<div><br></div>\n<div> </div>\n<div><br></div>\n<div>After you submit your assignment, click Next to complete the Week 6 Discussion.</div>\n<div><br></div>\n<div><br></div>\n<div>Points</div>\n<div>100</div>\n<div>Submitting</div>\n<div>a text entry box or a file upload</div>\n<div>Due  For  Available from  Until</div>\n<div>Mar 5Mar 5 at 11:59pm  Everyone  -N/A  -N/A</div>\n<div>Rubric</div>\n<div>  </div>\n<div><h3>Warm-up Rubric</h3></div>",
  "context": "From document: Week 6 Canvas Data Dump: — chunk 12 (chunk 12/25)",
  "tags": [
    "paragraph",
    "html",
    "chunked",
    "chunk-strategy-markdown-semantic"
  ],
  "category": "programming",
  "documentId": "4df809ce4a40f6ef965c1ad700e9ab52",
  "relatedUnits": [],
  "keywords": [
    "your",
    "warm",
    "week",
    "weekly",
    "writing"
  ],
  "sectionType": "paragraph",
  "hierarchyLevel": 0
}