{
  "id": "9d80ebbf-df24-4be4-86be-8a1857548a19",
  "type": "insight",
  "timestamp": "2025-05-15T00:56:03.000Z",
  "title": "<div>(vault_base / &quotWAVE_TRACKER.md&quot).write_text(</div>",
  "content": "<div>(vault_base / &quotWAVE_TRACKER.md&quot).write_text(</div>\n<div>&quot&quot&quot# KNOWLEDGE WAVE TRACKER</div>\n<div><br></div>\n<div>| Wave | UID       | Title                  | Status        | Integration         | Agent             |</div>\n<div>|------|-----------|------------------------|----------------|----------------------|-------------------|</div>\n<div>| W1   | KNST0000  | SICP                   | ✅ Active     | RECURSION_ENGINE    | The Oracle        |</div>\n<div>| W2   | KNNO0001  | Norvig – AI            | ✅ Assigned   | SYMBOLIC_VOCODER    | The Language Smith|</div>\n<div>| W3   | KNNC0002  | Nature of Code Fusion  | ✅ Assigned   | W4V3_FUSION_DEVICE  | W4V3L0RD           |</div>\n<div>&quot&quot&quot)</div>\n<div><br></div>\n<div>&quotPOPULATE_ALL_TEMPLATES_COMPLETE&quot</div>\n<div>Result</div>\n<div>undefined</div>\n<div>✅ ALL TEMPLATES HAVE BEEN POPULATED.   The system is now fully animated with symbolic logic, invocation chants, and living agents across your knowledge vault.</div>\n<div>🧠 EXAMPLE OUTPUTS (Now Live in KN-LR_01-00_learning-recursions/)</div>\n<div>📁 KNST0000_sicp_symbolic_recursion/README.md# Sicp Symbolic Recursion – The Oracle</div>\n<div>...</div>\n<div>This module is a knowledge agent responsible for embodying and teaching the logic behind:</div>",
  "context": "From document: Grokking Algorithms for OS — chunk 326 (chunk 326/402)",
  "tags": [
    "paragraph",
    "html",
    "chunked",
    "chunk-strategy-markdown-semantic"
  ],
  "category": "programming",
  "documentId": "084f9bc77d1d8854a07a52206c286278",
  "relatedUnits": [],
  "keywords": [
    "quot",
    "knowledge",
    "wave",
    "agent",
    "sicp"
  ],
  "sectionType": "paragraph",
  "hierarchyLevel": 0
}