{
  "id": "9d9fb570-7c9e-49da-95a0-f267bba49f29",
  "type": "insight",
  "timestamp": "2025-02-12T19:07:35.000Z",
  "title": "<div><br></div>",
  "content": "<div><br></div>\n<div>Read what you wrote for the Week 1 Warm-Up assignment. Was it interesting? Does it sound like your voice? Could it have been better? Write your thoughts in 250 words on what you wrote.</div>\n<div><br></div>\n<div>Save your completed Week 2 Weekly Writing Warm-Up using the proper naming convention.</div>\n<div>Estimated Time for Completion</div>\n<div>The estimated time to complete this activity is 5 minutes.</div>\n<div><br></div>\n<div>  </div>\n<div><h3>Warm-up Rubric</h3></div>\n<div>You've already rated students with this rubric. Any major changes could affect their assessment results.</div>\n<div>Warm-up Rubric</div>\n<div>Criteria  Ratings  Pts</div>\n<div>This criterion is linked to a Learning OutcomeEvaluation</div>\n<div>Weekly Writing Warmup assessment criteria.</div>\n<div>100 pts</div>\n<div>Full Credit</div>\n<div>Submission reflects completion of the guidelines and prompts outlined in the instructions and the required time spent writing.</div>\n<div>50 pts</div>\n<div>Partial Credit</div>\n<div>Submission reflects on at least half of the guidelines and prompts outlined in the instructions and the required time spent writing.</div>\n<div>0 pts</div>\n<div>No Credit</div>",
  "context": "From document: Weeks 1 - 6 Canvas Data Dump — chunk 53 (chunk 53/188)",
  "tags": [
    "paragraph",
    "html",
    "chunked",
    "chunk-strategy-markdown-semantic"
  ],
  "category": "writing",
  "documentId": "1b21c03b1f1909954adca118a79b0158",
  "relatedUnits": [],
  "keywords": [
    "warm",
    "writing",
    "time",
    "your",
    "this"
  ],
  "sectionType": "paragraph",
  "hierarchyLevel": 0
}