{
  "id": "a9e76ded-a307-495c-aa4b-7c9eacfe0bd2",
  "type": "insight",
  "timestamp": "2025-07-03T12:59:32.000Z",
  "title": "<div><br></div>",
  "content": "<div><br></div>\n<div>I then you could make it.</div>\n<div><br></div>\n<div>So you have your Greek mythology shit.</div>\n<div><br></div>\n<div>The card will still be time warp and functions, like, you know what I mean?</div>\n<div><br></div>\n<div>Play to mana, you know, whatever the card does.</div>\n<div><br></div>\n<div>But instead of it being the time warp art and everything, you can make it, you know, whatever.</div>\n<div><br></div>\n<div>Oh, shit.</div>\n<div><br></div>\n<div>And I can't think of a mythological reference for that.</div>\n<div><br></div>\n<div>You can make it, I don't know.</div>\n<div><br></div>\n<div>No, I know what you're saying, though, yeah, like, um..</div>\n<div><br></div>\n<div>You resk it something like Totally.</div>\n<div><br></div>\n<div>That. A sense..</div>\n<div><br></div>\n<div>So, are there any other, like, DVs the only fusion based mythology that I know?</div>\n<div><br></div>\n<div>Do you know any other fusion based mythologies?</div>\n<div><br></div>\n<div>Like, where they Or you know, I mean, you know what I'm saying?</div>\n<div><br></div>\n<div>What do they call that?</div>\n<div><br></div>\n<div>It's not called mythology and everything, but it's called.</div>\n<div><br></div>",
  "context": "From document: Title: Revolutionizing the Trading Card Market — chunk 58 (chunk 58/108)",
  "tags": [
    "paragraph",
    "html",
    "chunked",
    "chunk-strategy-markdown-semantic"
  ],
  "category": "general",
  "documentId": "914bdb636f4b4d776816c4203c5e58af",
  "relatedUnits": [],
  "keywords": [
    "know",
    "like",
    "what",
    "that",
    "make"
  ],
  "sectionType": "paragraph",
  "hierarchyLevel": 0
}