{
  "id": "abf28140-be00-476a-8506-caaedb46fcb6",
  "type": "insight",
  "timestamp": "2025-06-30T13:57:29.000Z",
  "title": "<div><br></div>",
  "content": "<div><br></div>\n<div><br></div>\n<div><br></div>\n<div>---</div>\n<div><br></div>\n<div>Tap below this line, press the 📎 icon, and record your answer.</div>\n<div><br></div>\n<div>---</div>\n<div><br></div>\n<div><h2>5. Checking Eligibility ✅</h2></div>\n<div>Is the total value of the estate’s bank accounts and other non-exempt property under $75,000? (Or, has it been more than two years since they passed away?)</div>\n<div><br></div>\n<div><br></div>\n<div>---</div>\n<div><br></div>\n<div>Tap below this line, press the 📎 icon, and record your answer.</div>\n<div><br></div>\n<div>---</div>\n<div><br></div>\n<div><h2>6. Exempt Property 🚗 🏠</h2></div>\n<div>Please state the year, make, and model of any vehicles. Also, please mention if they owned their primary home (their homestead).</div>\n<div><br></div>\n<div><br></div>\n<div>---</div>\n<div><br></div>\n<div>Tap below this line, press the 📎 icon, and record your answer.</div>\n<div><br></div>\n<div>---</div>\n<div><br></div>\n<div><h2>7. Other Assets 💰</h2></div>\n<div>Now, for all other assets like bank accounts or financial accounts, please state the name of the bank and the estimated value of the account.</div>\n<div><br></div>\n<div><br></div>\n<div>---</div>",
  "context": "From document: Probate Paperwork Interview — chunk 3 (chunk 3/5)",
  "tags": [
    "paragraph",
    "html",
    "chunked",
    "chunk-strategy-markdown-semantic"
  ],
  "category": "general",
  "documentId": "bab62be543c9218ee418bb86bd762469",
  "relatedUnits": [],
  "keywords": [
    "below",
    "this",
    "line",
    "press",
    "icon"
  ],
  "sectionType": "paragraph",
  "hierarchyLevel": 0
}