{
  "id": "b65ff14f-6a15-41f6-bf2b-0fac161ad0e8",
  "type": "insight",
  "timestamp": "2025-05-17T02:49:18.000Z",
  "title": "<div><tt><br></tt></div>",
  "content": "<div><tt><br></tt></div>\n<div><tt>### `✶ Generative Lifestyle &amp Ambient Environments (GEN+ / RIT+)`  </tt></div>\n<div><tt>Live inside the story: generative music, ASMR-style environments, dream dialogues, memory-soundwalks. The OS listens and reflects. Play a sound generated from the waveform of your past year. Watch your words become light. Let your archive whisper to you in the voice of your future self. This is passive, immersive mythology. An ambient haunt of the self.</tt></div>\n<div><tt><br></tt></div>\n<div><tt>### `✶ Translation, Conlang, and Multilingual Myth Systems (LANG+ / GEN+)`  </tt></div>\n<div><tt>MYTHOS can operate across multiple languages and symbolic alphabets. It includes a constructed language interface that lets users build and evolve private or mythic tongues over time. It treats language like circuitry—composable, remixable, sonically alive. Your conlang becomes a **sacred key**—a symbolic grammar tied to identity, time, and recursion.</tt></div>\n<div><tt><br></tt></div>\n<div><tt>---</tt></div>\n<div><tt><br></tt></div>\n<div><tt>## 🔧 SYSTEM COMPONENTS (RECURSIVELY SCAFFOLDED)</tt></div>\n<div><tt><br></tt></div>\n<div><tt>| Component      | Description                                                                 |</tt></div>",
  "context": "From document: # Character Engine POV Critique — chunk 117 (chunk 117/206)",
  "tags": [
    "paragraph",
    "html",
    "chunked",
    "chunk-strategy-markdown-semantic"
  ],
  "category": "writing",
  "documentId": "97f62abc7c2459304ad6df9f4596a27a",
  "relatedUnits": [],
  "keywords": [
    "your",
    "generative",
    "ambient",
    "environments",
    "self"
  ],
  "sectionType": "paragraph",
  "hierarchyLevel": 0
}