{
  "id": "bf67dfb9-dc30-46f5-af90-4b3a06d6aee6",
  "type": "insight",
  "timestamp": "2025-02-12T16:23:09.000Z",
  "title": "<div>After you finish this page, click Next to continue to the Week 4 Knowledge ",
  "content": "<div>After you finish this page, click Next to continue to the Week 4 Knowledge Check: Evaluating Thesis Statements. </div>\n<div><br></div>\n<div><br></div>\n<div><h2>Week 4 | Knowledge Check: Evaluating Thesis Statements</h2></div>\n<div>Evaluating Thesis Statements</div>\n<div>Instructions</div>\n<div>Read each thesis statement and determine if they are strong or weak. Flip the card to check your work!</div>\n<div><br></div>\n<div><br></div>\n<div><br></div>\n<div>After you finish this page, click Next to continue to Specifics of Grammar.</div>\n<div><br></div>\n<div><br></div>\n<div><h2>Week 4 | Specifics of Grammar</h2></div>\n<div>Specifics of Grammar</div>\n<div>We will visit three grammar topics before we end our lessons: misplaced modifiers, dangling modifiers, and run-on sentences.</div>\n<div><br></div>\n<div>A misplaced modifier is a word, phrase, or clause that needs to be in the right place in relation to the word it describes. It is incorrectly positioned in relation to the word it describes or modifies. The result is a sentence that lacks coherence, feels clumsy, or conveys unintended meanings.</div>\n<div><br></div>\n<div>An example might be: Running down the street, the dog chased the ball.</div>",
  "context": "From document: Week 4 Canvas Data Dump: — chunk 12 (chunk 12/29)",
  "tags": [
    "paragraph",
    "html",
    "chunked",
    "chunk-strategy-markdown-semantic"
  ],
  "category": "general",
  "documentId": "d23737d0f113a71804bbfe76a4d190ca",
  "relatedUnits": [],
  "keywords": [
    "thesis",
    "grammar",
    "week",
    "check",
    "evaluating"
  ],
  "sectionType": "paragraph",
  "hierarchyLevel": 0
}