{
  "id": "cba2f71c-68a3-43df-a603-7b5b5a8255cb",
  "type": "insight",
  "timestamp": "2025-07-03T12:59:32.000Z",
  "title": "<div><br></div>",
  "content": "<div><br></div>\n<div>So, if you can do something like that for the cards, where there's like a news update, like, oh, these magic cards just got banned.</div>\n<div><br></div>\n<div>Like, since these seven cards just got banned, here's the seven cards that are similar to them that people areing can be fish on and start buying.</div>\n<div><br></div>\n<div>Like, you know what I mean?</div>\n<div><br></div>\n<div>Like, if you could get, like predictive data based off like, what's going on in these card games and the, and like the sales and like the hype of these cards and and, like, things like that, and like like, the older people do buyouts on old cards all the time.</div>\n<div><br></div>\n<div>Like all of a sudden, like, you'll see, like some will buy every single maxim rule for magic that exists on the market, so that they own all of them. Make the price that they want.</div>\n<div><br></div>\n<div>So, like, there are like very, there are like sophisticated investors that do things on these platforms, like, like big buyouts and spend, like tens and hundreds of thousands of dollars.</div>\n<div><br></div>\n<div>So, like, let's say you facilitate $100,000 buyout of a single card , and you got 1% of that.</div>",
  "context": "From document: Title: Revolutionizing the Trading Card Market — chunk 8 (chunk 8/108)",
  "tags": [
    "paragraph",
    "html",
    "chunked",
    "chunk-strategy-markdown-semantic"
  ],
  "category": "general",
  "documentId": "914bdb636f4b4d776816c4203c5e58af",
  "relatedUnits": [],
  "keywords": [
    "like",
    "that",
    "cards",
    "these",
    "there"
  ],
  "sectionType": "paragraph",
  "hierarchyLevel": 0
}