{
  "id": "ee7451a8-2c54-43fe-8e3d-71e026c0dc22",
  "type": "insight",
  "timestamp": "2025-02-17T23:20:46.000Z",
  "title": "<div><tt><br></tt></div>",
  "content": "<div><tt><br></tt></div>\n<div><tt><br></tt></div>\n<div><tt>Your analysis effectively captures the depth of symbolism in A Worn Path, particularly in how the worn path and the pheasant illustrate Phoenix Jackson’s perseverance and sacrifice. I appreciate how you highlight the path as both a literal and metaphorical journey, representing not just her physical struggle but also the hardships she has endured throughout her life. Your point about her unwavering commitment to her grandson despite these obstacles is especially powerful.</tt></div>\n<div><tt><br></tt></div>\n<div><tt>I also find your interpretation of the pheasant intriguing. The idea that it represents a potential distraction or test of Phoenix’s resolve adds another layer of meaning to her journey. It’s interesting how, despite being startled and falling, she refuses to be deterred. This moment reinforces the theme of resilience, showing that setbacks do not define her—her ability to get back up does.</tt></div>\n<div><tt><br></tt></div>\n<div><tt>Building on your analysis, I think another compelling symbol in the story is Phoenix’s name itself. Like the mythical phoenix, she repeatedly endures hardship and “rises” again, continuing her journey despite her age, fatigue, and the difficulties she faces. This aligns well with the themes of perseverance and sacrifice, as her entire existence seems to be centered around enduring hardships for the sake of someone she loves.</tt></div>",
  "context": "From document: Student Submission: — chunk 5 (chunk 5/134)",
  "tags": [
    "paragraph",
    "html",
    "chunked",
    "chunk-strategy-markdown-semantic"
  ],
  "category": "research",
  "documentId": "f724cc82d2d987b6ae9e11ab05d297ca",
  "relatedUnits": [],
  "keywords": [
    "your",
    "phoenix",
    "path",
    "journey",
    "despite"
  ],
  "sectionType": "paragraph",
  "hierarchyLevel": 0
}