{
  "id": "f6326268-3d77-444c-9bc4-6d9a39af5e63",
  "type": "insight",
  "timestamp": "2025-05-15T00:56:03.000Z",
  "title": "<div><br></div>",
  "content": "<div><br></div>\n<div># SYMBOLIC FUSION – Data-Intensive Applications (Kleppmann)</div>\n<div><br></div>\n<div>## Concept:</div>\n<div>This book teaches how to manage, transform, and scale knowledge as live data. It maps to `W4V3_FUSION_DEVICE` and archival fluidity logic.</div>\n<div><br></div>\n<div>## OS Modules Affected:</div>\n<div>- `ARCHIVE_ENGINE`</div>\n<div>- `TEMP0R4L_STACKS`</div>\n<div>- `DATAWAVES/`</div>\n<div>[3] ::MYTH_AGENT_AUTO</div>\n<div>Generating MYTH_AGENT.md file for each book with symbolic persona.</div>\n<div>✅ Example: KNTP0201_plateaus_ai_modularity/MYTH_AGENT.md&lt!-- UID: KN-TP_02-01 --&gt</div>\n<div><br></div>\n<div># MYTH AGENT: THE SWARM ENGINE</div>\n<div><br></div>\n<div>## Symbol: Fractal Mesh  </div>\n<div>## Domain: Modular Complexity / AI Co-Agents  </div>\n<div>## Invocation: &quotLet the many think as one.&quot</div>\n<div><br></div>\n<div>## Function in System:</div>\n<div>- Emergent system logic</div>\n<div>- Fragmentation-resistance</div>\n<div>- Cross-thread identity weaving</div>\n<div>[4] ::EXPORT.ZIP (Pending Live Export Trigger)</div>\n<div>Contents:REGE_OS/</div>\n<div>└── L1_LEARNING_CORE/</div>\n<div>    ├── [12 UID folders]</div>\n<div>    ├── WAVE_TRACKER.md</div>",
  "context": "From document: Grokking Algorithms for OS — chunk 300 (chunk 300/402)",
  "tags": [
    "paragraph",
    "html",
    "chunked",
    "chunk-strategy-markdown-semantic"
  ],
  "category": "programming",
  "documentId": "084f9bc77d1d8854a07a52206c286278",
  "relatedUnits": [],
  "keywords": [
    "symbolic",
    "data",
    "book",
    "live",
    "logic"
  ],
  "sectionType": "paragraph",
  "hierarchyLevel": 0
}