{
  "id": "fcedb313-fc98-406c-944a-a5ecfbe5b644",
  "type": "insight",
  "timestamp": "2024-03-30T06:19:33.000Z",
  "title": "<div>Digital Marketing Stack</div>",
  "content": "<div>Digital Marketing Stack</div>\n<div><br></div>\n<div>Content Creation and Management</div>\n<div><br></div>\n<div>  •  AI Writing Assistants</div>\n<div>  •  Software Name:</div>\n<div>  •  Pricing:</div>\n<div>  •  Content Management System (CMS)</div>\n<div>  •  Software Name:</div>\n<div>  •  Pricing:</div>\n<div>  •  Graphic Design Tools</div>\n<div>  •  Software Name:</div>\n<div>  •  Pricing:</div>\n<div><br></div>\n<div>SEO and Content Optimization</div>\n<div><br></div>\n<div>  •  SEO Tools</div>\n<div>  •  Software Name:</div>\n<div>  •  Pricing:</div>\n<div>  •  Content Optimization Tools</div>\n<div>  •  Software Name:</div>\n<div>  •  Pricing:</div>\n<div><br></div>\n<div>Social Media Management</div>\n<div><br></div>\n<div>  •  Social Media Scheduling</div>\n<div>  •  Software Name:</div>\n<div>  •  Pricing:</div>\n<div>  •  Social Media Monitoring and Analytics</div>\n<div>  •  Software Name:</div>\n<div>  •  Pricing:</div>\n<div><br></div>\n<div>Email Marketing</div>\n<div><br></div>\n<div>  •  Email Marketing Platforms</div>\n<div>  •  Software Name:</div>\n<div>  •  Pricing:</div>\n<div><br></div>\n<div>Advertising</div>\n<div><br></div>\n<div>  •  PPC and Ad Management Tools</div>\n<div>  •  Software Name:</div>",
  "context": "From document: Digital Marketing Stack — chunk 1 (chunk 1/3)",
  "tags": [
    "paragraph",
    "html",
    "chunked",
    "chunk-strategy-markdown-semantic"
  ],
  "category": "general",
  "documentId": "97ed2e0dff72e5a0f4ae5529604778a2",
  "relatedUnits": [],
  "keywords": [
    "software",
    "name",
    "pricing",
    "content",
    "management"
  ],
  "sectionType": "paragraph",
  "hierarchyLevel": 0
}